ydata/datascience/__init__.py
ydata/datascience/common/__init__.py
ydata/datascience/common/anonymizer.py
ydata/datascience/common/privacy.py
ydata_datascience-0.6.0.dist-info/METADATA
ydata_datascience-0.6.0.dist-info/WHEEL
ydata_datascience-0.6.0.dist-info/top_level.txt
ydata_datascience-0.6.0.dist-info/RECORD
