Metadata-Version: 2.1
Name: ydata-datascience
Version: 0.6.0
Summary: Data science functionalities for all python packages at YData
Home-page: https://github.com/ydataai/python-core
Author: YData
Author-email: developers@ydata.ai
Classifier: Intended Audience :: Developers
Classifier: Programming Language :: Python :: 3 :: Only
Classifier: Topic :: Software Development :: Libraries :: Python Modules
